courseraresearchexports/__init__.py
courseraresearchexports/main.py
courseraresearchexports/commands/__init__.py
courseraresearchexports/commands/containers.py
courseraresearchexports/commands/db.py
courseraresearchexports/commands/jobs.py
courseraresearchexports/commands/utils.py
courseraresearchexports/commands/version.py
courseraresearchexports/constants/__init__.py
courseraresearchexports/constants/api_constants.py
courseraresearchexports/constants/container_constants.py
courseraresearchexports/constants/db_constants.py
courseraresearchexports/containers/__init__.py
courseraresearchexports/containers/client.py
courseraresearchexports/containers/utils.py
courseraresearchexports/db/__init__.py
courseraresearchexports/db/db.py
courseraresearchexports/exports/__init__.py
courseraresearchexports/exports/api.py
courseraresearchexports/exports/utils.py
courseraresearchexports/models/ClickstreamDownloadLinksRequest.py
courseraresearchexports/models/ContainerInfo.py
courseraresearchexports/models/ExportDb.py
courseraresearchexports/models/ExportRequest.py
courseraresearchexports/models/ExportRequestWithMetadata.py
courseraresearchexports/models/__init__.py
courseraresearchexports/models/utils.py
courseraresearchexports/sql/demographic_survey.sql
courseraresearchexports/sql/enrollments.sql
courseraresearchexports-0.0.27.dist-info/LICENSE
courseraresearchexports-0.0.27.dist-info/METADATA
courseraresearchexports-0.0.27.dist-info/WHEEL
courseraresearchexports-0.0.27.dist-info/entry_points.txt
courseraresearchexports-0.0.27.dist-info/top_level.txt
courseraresearchexports-0.0.27.dist-info/RECORD
