Metadata-Version: 2.1
Name: courseraresearchexports
Version: 0.0.27
Summary: Command line tool for convenient access to Coursera Research Data Exports.
Home-page: https://github.com/coursera/courseraresearchexports
Author: Chris Liu
Author-email: cliu@coursera.org
License: Apache
Keywords: coursera
Platform: UNKNOWN
Classifier: Development Status :: 5 - Production/Stable
Classifier: License :: OSI Approved :: Apache Software License
Classifier: Programming Language :: Python :: 2.7
Requires-Dist: argcomplete (>=1.4.1)
Requires-Dist: courseraoauth2client (>=0.0.1)
Requires-Dist: requests (<2.11,>=2.7.0)
Requires-Dist: docker-py (>=1.2.3)
Requires-Dist: tqdm (>=4.8.4)
Requires-Dist: tabulate (>=0.7.5)
Requires-Dist: python-dateutil (>=2.5.3)
Requires-Dist: SQLAlchemy (>=1.0.15)
Requires-Dist: psycopg2 (>=2.6.2)
